[
  {
    "model": "workflows.abstractwidget",
    "fields": {
      "name": "Extract results",
      "action": "core_extract_results",
      "wsdl": "",
      "wsdl_method": "",
      "description": "This widget is useful for preparing results for visualization using the Viper widget.",
      "category": "01ad639d-acb8-45c0-bc5e-bc8739bb4c95",
      "visualization_view": "",
      "streaming_visualization_view": "",
      "interactive": false,
      "interaction_view": "",
      "post_interact_action": "",
      "image": "",
      "treeview_image": "",
      "static_image": "",
      "has_progress_bar": false,
      "is_streaming": false,
      "order": 1,
      "uid": "3ddf7c0b-6b63-46f2-9a39-b1270c51b7c1",
      "package": "cf_core",
      "always_save_results": false,
      "windows_queue": false
    }
  },
  {
    "model": "workflows.abstractinput",
    "fields": {
      "name": "Name",
      "short_name": "nam",
      "description": "",
      "variable": "name",
      "widget": "3ddf7c0b-6b63-46f2-9a39-b1270c51b7c1",
      "required": false,
      "parameter": false,
      "multi": false,
      "default": "",
      "parameter_type": "text",
      "order": 1,
      "uid": "01af240a-0a52-4c7d-9c82-9ac1bd0982d8"
    }
  },
  {
    "model": "workflows.abstractinput",
    "fields": {
      "name": "Precision",
      "short_name": "pre",
      "description": "",
      "variable": "precision",
      "widget": "3ddf7c0b-6b63-46f2-9a39-b1270c51b7c1",
      "required": false,
      "parameter": false,
      "multi": false,
      "default": "",
      "parameter_type": null,
      "order": 1,
      "uid": "119a7253-5c19-468a-82b7-91b95fdecf36"
    }
  },
  {
    "model": "workflows.abstractinput",
    "fields": {
      "name": "F score",
      "short_name": "f",
      "description": "",
      "variable": "fscore",
      "widget": "3ddf7c0b-6b63-46f2-9a39-b1270c51b7c1",
      "required": false,
      "parameter": false,
      "multi": false,
      "default": "",
      "parameter_type": null,
      "order": 1,
      "uid": "46771a73-77e1-40d1-9a53-1a4ffed49f21"
    }
  },
  {
    "model": "workflows.abstractinput",
    "fields": {
      "name": "Area under curve",
      "short_name": "auc",
      "description": "",
      "variable": "auc",
      "widget": "3ddf7c0b-6b63-46f2-9a39-b1270c51b7c1",
      "required": false,
      "parameter": false,
      "multi": false,
      "default": "",
      "parameter_type": null,
      "order": 1,
      "uid": "9a580915-5bef-445b-9195-13711ee0080d"
    }
  },
  {
    "model": "workflows.abstractinput",
    "fields": {
      "name": "Runtime",
      "short_name": "bmk",
      "description": "",
      "variable": "runtime",
      "widget": "3ddf7c0b-6b63-46f2-9a39-b1270c51b7c1",
      "required": false,
      "parameter": false,
      "multi": false,
      "default": "",
      "parameter_type": null,
      "order": 1,
      "uid": "9d2b4fd5-e977-41c0-a857-ef9c00499c0f"
    }
  },
  {
    "model": "workflows.abstractinput",
    "fields": {
      "name": "Accuracy",
      "short_name": "acc",
      "description": "",
      "variable": "accuracy",
      "widget": "3ddf7c0b-6b63-46f2-9a39-b1270c51b7c1",
      "required": false,
      "parameter": false,
      "multi": false,
      "default": "",
      "parameter_type": null,
      "order": 1,
      "uid": "af085bcc-39a0-4d04-b709-6fe6fd953920"
    }
  },
  {
    "model": "workflows.abstractinput",
    "fields": {
      "name": "Recall",
      "short_name": "rec",
      "description": "",
      "variable": "recall",
      "widget": "3ddf7c0b-6b63-46f2-9a39-b1270c51b7c1",
      "required": false,
      "parameter": false,
      "multi": false,
      "default": "",
      "parameter_type": null,
      "order": 1,
      "uid": "ed759223-3e5d-4f27-8fa3-26000808fda0"
    }
  },
  {
    "model": "workflows.abstractoutput",
    "fields": {
      "name": "Results",
      "short_name": "res",
      "description": "results",
      "variable": "results",
      "widget": "3ddf7c0b-6b63-46f2-9a39-b1270c51b7c1",
      "order": 1,
      "uid": "bb0d42b8-dc77-4b01-b6ad-480d52e917c2"
    }
  }
]